{
  "studio": "OLM",
  "source": "Video Game",
  "episodes": 26,
  "trailerYoutubeId": "SX4dy9KT51A",
  "averageScore": 55,
  "relatedAnimeIds": [],
  "zh": "邁向命運指引的戰鬥旅程。距離凱瑟王埋葬魔王安格蒙已經過了一一百年。見習騎士凱瑟生活在這個和平的時代。然而，鄰近地區出現魔族的消息，讓凱瑟的命運開始轉動。在大賢者的引導下，獲得可靠同伴的凱瑟踏上了旅程。為了尋找被封印的聖劍……。",
  "ja": "運命が導く戦いの旅路へ。カイル王が魔王アングムンドを葬り去って100年。平和な時代に見習い騎士のカーセルは生きていた。だが、魔族が近隣に現れたとの知らせからカーセルの運命が動き始める。大賢者に導かれ、頼れる仲間を得たカーセルは旅立つ。封印されし聖剣を求めて・・・。",
  "en": "Towards the journey of battle guided by destiny. 100 years have passed since King Kyle buried the Demon Lord Angmund. Apprentice Knight Kasel lived in a time of peace. However, his fate begins to turn upon receiving news of demons appearing in the neighborhood. Guided by the Great Sage and gaining reliable companions, Kasel sets off on a journey. In search of the sealed Holy Sword..."
}