{
  "studio": "TROYCA",
  "source": "Video Game",
  "episodes": 15,
  "trailerYoutubeId": "JwYIdlj4c7A",
  "averageScore": 81,
  "relatedAnimeIds": [
    "anilist-87495",
    "anilist-127721",
    "anilist-103417",
    "anilist-114987",
    "anilist-138687",
    "anilist-125274",
    "anilist-103394",
    "anilist-87179",
    "anilist-103396",
    "anilist-103398",
    "anilist-103393",
    "anilist-103397",
    "anilist-101169",
    "anilist-103392",
    "anilist-103395",
    "anilist-103948",
    "anilist-114434",
    "anilist-114958",
    "anilist-186346",
    "anilist-191893",
    "anilist-186347",
    "anilist-114922",
    "anilist-148816",
    "anilist-150848",
    "anilist-186586",
    "anilist-155841",
    "anilist-128890",
    "anilist-155843"
  ]
}