{
  "studio": "Studio DEEN",
  "source": "Light Novel",
  "episodes": 12,
  "trailerYoutubeId": "Eks6OyQNoEU",
  "averageScore": 65,
  "relatedAnimeIds": [
    "anilist-85494",
    "anilist-85495",
    "anilist-199217"
  ],
  "zh": "伴杭彼方突然遭到跟蹤狂刺殺，醒來後發現自己竟然轉生為最弱的哥布林「哥布朗」。憑藉著越吃越強的【吸食能力】，經歷了非凡的進化後，他轉眼間就登上了哥布林族群的頂點——在弱肉強食的異世界中，與才華洋溢的夥伴們共同生存的怪物轉生奇幻故事就此展開！",
  "ja": "ストーカーに突如刺殺された伴杭彼方。目を覚ますと、最弱のゴブリン「ゴブ朗」として転生していた。喰えば喰うほど強くなる【吸喰能力】を駆使し、異常な進化を遂げた彼は、あっという間にゴブリンの群れの頂点へと登りつめる——。弱肉強食の異世界で、有能な仲間たちと共に生き抜く怪物転生ファンタジーが今幕を開ける！",
  "en": "Kanata Tomokui is suddenly stabbed to death by a stalker, only to wake up and find himself reincarnated as Gobrou, the weakest of goblins. Relying on his [Absorption] ability, which allows him to grow stronger the more he eats, he undergoes extraordinary evolutions and quickly climbs to the very top of the goblin hierarchy. A monster reincarnation fantasy story unfolds as he and his talented companions struggle to survive in a dog-eat-dog fantasy world!"
}