{
  "relatedAnimeIds": [
    "anilist-16732",
    "anilist-20654",
    "anilist-56036",
    "anilist-21753"
  ],
  "zh": "輕鬆治癒系美少女動畫的金字塔《黃金拼圖》，其集大成的最終篇章便是《劇場版 黃金拼圖 謝謝你!!》！有時搞笑，總是開朗，率真且閃閃發光的每一天。請在戲院裡盡情享受她們最後的高中生活吧！",
  "ja": "ゆるふわ美少女アニメの金字塔「きんいろモザイク」の\n集大成となるファイナルエピソードが劇場版「きんいろモザイクThank You!!」です！\n\nときにおかしく、いつも明るく、まっすぐできらきらした日々。\n彼女たちの最後の高校生活を、劇場でお楽しみください！",
  "en": "The pinnacle of fluffy, heartwarming beautiful girl anime, \"Kin-iro Mosaic,\" reaches its grand culmination with the final episode, the movie \"Kin-iro Mosaic Thank You!!\" Sometimes funny, always cheerful, their straightforward and sparkling days. Please enjoy their final high school life at the theater!",
  "studio": "AXsiZ",
  "source": "Manga",
  "episodes": 1,
  "trailerYoutubeId": "jC6f2BgK0jg",
  "averageScore": 75
}