{
  "studio": "Toei Animation",
  "source": "Original",
  "episodes": 50,
  "trailerYoutubeId": "fa26uE6WgbY",
  "averageScore": 78,
  "relatedAnimeIds": [
    "anilist-7645",
    "anilist-8133",
    "anilist-9288",
    "anilist-9893",
    "anilist-12191",
    "anilist-12221",
    "anilist-16419",
    "anilist-98059",
    "anilist-142080",
    "anilist-603",
    "anilist-1534",
    "anilist-1932",
    "anilist-5684",
    "anilist-71121",
    "anilist-15307",
    "anilist-16442",
    "anilist-20577",
    "anilist-20549",
    "anilist-21137",
    "anilist-21506",
    "anilist-21504",
    "anilist-100661",
    "anilist-101908",
    "anilist-105857",
    "anilist-112748",
    "anilist-126905",
    "anilist-157883",
    "anilist-159429",
    "anilist-171030",
    "anilist-185073",
    "anilist-202957",
    "anilist-55928",
    "anilist-9979",
    "anilist-10736",
    "anilist-11569",
    "anilist-96351",
    "anilist-135864",
    "anilist-55710",
    "anilist-10821",
    "anilist-188394",
    "anilist-105042",
    "anilist-17357",
    "anilist-204480",
    "anilist-105044",
    "anilist-21323",
    "anilist-99642",
    "anilist-101846",
    "anilist-98891",
    "anilist-101101",
    "anilist-106858",
    "anilist-143176",
    "anilist-144687",
    "anilist-154678",
    "anilist-5753"
  ],
  "zh": "夢想是成為公主的春野遙，於新的學期正式成為寄宿學校貴族學園的國中一年級生，準備展開期待已久的新生活。就在此時，她目睹邪惡勢力把人通往夢想的「門」緊密封閉，並染上濃厚的絕望。然後在機緣巧合之下，她集齊了希望王國彼方王子誓死守護的公主香水及裝扮鑰匙，變身成為光之美少女——花神天使，開始奮勇對抗敵人。",
  "ja": "プリンセスになることを夢見る春野はるかは、新学期から全寮制のノーブル学園の中学1年生となり、待ちに待った新生活をスタートさせる。そんな時、人々の夢への「扉」を閉ざし、絶望に染め上げる邪悪な勢力を目撃する。そしてひょんなことから、ホープキングダムのカナタ王子が命懸けで守り抜いたプリンセスパフュームとドレスアップキーを揃え、光の美少女・キュアフローラに変身し、敵に立ち向かう。",
  "en": "Haruka Haruno, who dreams of becoming a princess, officially starts her long-awaited new life as a first-year middle school student at the boarding school Noble Academy in the new semester. Just then, she witnesses an evil force tightly sealing the \"door\" to people's dreams and painting them in deep despair. By chance, she gathers the Princess Perfume and Dress Up Keys, which Prince Kanata of the Hope Kingdom swore to protect with his life, transforming into a Pretty Cure—Cure Flora—and bravely fighting against the enemy."
}