{
  "studio": "feel.",
  "source": "Original",
  "episodes": 1,
  "averageScore": 71,
  "relatedAnimeIds": [
    "anilist-98202"
  ],
  "zh": "茜與小太郎。\n國三時第一次被分到同班，相識的兩人。\n同班同學、社團夥伴、教師、父母……與周圍的關聯，自己的成長。\n在那個一邊被變化與不安追著，一邊慌慌張張地向前飛奔的季節之中，稚嫩而又令人目眩的青春期之戀。",
  "ja": "茜と小太郎。\n中学3年生で初めて同じクラスになり、出会った二人。\nクラスメイト、部活の仲間、教師、親……周囲との関わり、そして自分自身の成長。\n変化と不安に追われながらも、慌ただしく駆け抜けていく季節の中で紡がれる、初々しくも眩しい思春期の恋。",
  "en": "Akane and Kotaro.\nIn their third year of middle school, the two are placed in the same class for the first time and meet.\nClassmates, club members, teachers, parents... their connections with their surroundings, and their own growth.\nIn that season where they are chased by changes and anxiety while frantically dashing forward, an innocent and dazzling adolescent love story unfolds."
}