{
  "studio": "Sunrise",
  "source": "Manga",
  "episodes": 1,
  "trailerYoutubeId": "UhJM5rVqaF8",
  "averageScore": 87,
  "relatedAnimeIds": [
    "anilist-918",
    "anilist-10643",
    "anilist-7472",
    "anilist-9735",
    "anilist-9969",
    "anilist-9863",
    "anilist-11771",
    "anilist-15487",
    "anilist-20760",
    "anilist-15417",
    "anilist-17259",
    "anilist-16395",
    "anilist-16916",
    "anilist-19469",
    "anilist-16894",
    "anilist-19759",
    "anilist-20603",
    "anilist-21303",
    "anilist-101816",
    "anilist-20755",
    "anilist-20725",
    "anilist-20996",
    "anilist-21235",
    "anilist-21170",
    "anilist-21678",
    "anilist-21804",
    "anilist-21588",
    "anilist-101102",
    "anilist-97985",
    "anilist-97889",
    "anilist-21377",
    "anilist-99714",
    "anilist-100784",
    "anilist-98034",
    "anilist-101925",
    "anilist-104580",
    "anilist-112625",
    "anilist-114129",
    "anilist-126819",
    "anilist-180367",
    "anilist-162890",
    "anilist-30044",
    "anilist-21501",
    "anilist-20882",
    "anilist-175573",
    "anilist-178436",
    "anilist-2951",
    "anilist-6945",
    "anilist-197474",
    "anilist-169000",
    "anilist-199621",
    "anilist-95458",
    "anilist-44022",
    "anilist-67755",
    "anilist-31414",
    "anilist-16718",
    "anilist-128896",
    "anilist-199793",
    "anilist-1050",
    "anilist-31814",
    "anilist-69883",
    "anilist-41652",
    "anilist-19669",
    "anilist-102093",
    "anilist-156053",
    "anilist-21864",
    "anilist-198373",
    "anilist-86949",
    "anilist-98703",
    "anilist-102836",
    "anilist-98704",
    "anilist-102839",
    "anilist-98525",
    "anilist-85604",
    "anilist-118031",
    "anilist-101999"
  ],
  "zh": "由於某種力量，讓銀時突然來到自己所不存在的未來世界。徬徨無助的他，此時邂逅了兩位年輕人：其中一個青年戴著眼鏡，抽出他別在腰間的洞爺湖木刀，將鬧事者一舉制伏；另一個則是與銀時服裝相似，帶著超大型犬的美女，這兩人竟然就是成長後的新八與神樂！更讓銀時難以置信的是，他除了目睹眾人在未來的模樣，更看見了衝擊性的事實…。究竟過去發生了什麼事？要如何才能改變這個沒有銀時、遍布黑暗與恐怖的未來呢？",
  "ja": "ある力によって、銀時は突如自分の存在しない未来の世界へ飛ばされてしまう。途方に暮れる彼の前に、二人の若者が現れる。一人は眼鏡をかけ、腰に差した洞爺湖の木刀で暴漢を一撃で制圧する青年。もう一人は銀時と似た服を着て、巨大な犬を連れた美女。なんとこの二人は、成長した新八と神楽だった！さらに銀時が信じられないことに、未来の仲間たちの姿を目撃しただけでなく、衝撃的な事実を目の当たりにする…。果たして過去に何があったのか？銀時が存在せず、闇と恐怖に包まれた未来を変えるにはどうすればいいのか？",
  "en": "Due to some mysterious power, Gintoki is suddenly transported to a future world where he does not exist. While wandering helplessly, he encounters two young people: one young man wearing glasses draws the Lake Touya wooden sword at his waist and subdues troublemakers in one fell swoop; the other is a beautiful woman wearing clothes similar to Gintoki's, accompanied by an exceptionally large dog. These two turn out to be the grown-up Shinpachi and Kagura! What's even more unbelievable for Gintoki is that besides witnessing everyone's future appearance, he sees a shocking reality... What exactly happened in the past? How can they change this future filled with darkness and terror where Gintoki does not exist?"
}