{
  "studio": "J.C.STAFF",
  "source": "Manga",
  "episodes": 24,
  "trailerYoutubeId": "IEkjbRs6LHo",
  "averageScore": 77,
  "relatedAnimeIds": [
    "anilist-165931"
  ],
  "zh": "作為異形眷屬之王的第 99 個祭品而被獻上的少女——莎莉菲。\n她接受了自己的命運，走向活祭儀式。\n然而在那裡，她卻發現了那個誰都不敢接近、被萬眾恐懼的國王「雷恩哈特」的真實面貌，並被迎娶為妃子。",
  "ja": "異形の眷属の王の99番目の生贄として捧げられた少女、サリフィ。\n彼女は自身の運命を受け入れ、生贄の儀式へと向かう。\nしかしそこで、誰もが近づくことを恐れる恐ろしい王・レオンハートの真実の姿を知り、妃として迎えられることになる。",
  "en": "Sariphi is a young girl offered as the 99th sacrifice to the terrifying King of Beasts.\nAccepting her fate, she heads to the sacrificial ceremony.\nHowever, there she discovers the true nature of the King, Leonhart, who is feared and shunned by all, and is ultimately taken as his royal consort."
}