{
  "studio": "Doga Kobo",
  "source": "Manga",
  "episodes": 12,
  "trailerYoutubeId": "-UYzSIUB8Lo",
  "averageScore": 70,
  "relatedAnimeIds": [
    "anilist-107138",
    "anilist-126425"
  ],
  "zh": "怕生的御宅族女大學生宮子，遇到了天使般的小學生！？\n在看到妹妹帶來的新朋友小花的瞬間，宮子就無法抑制住心跳！！\n她為了和小花成為朋友而奮鬥，但……\n「想要和超絕可愛的她做朋友」系小品喜劇，開幕♪",
  "ja": "人見知りのオタク女子大生みやこが出会ったのは、天使のような小学生！？\n妹が連れてきた新しい友達・花ちゃんを見た瞬間、みやこの鼓動は止まらない！！\nどうにか花ちゃんと友達になろうと奮闘するみやこだったが……。\n「超絶かわいい彼女と友達になりたい」系スケッチコメディ、開幕♪",
  "en": "Miyako, an introverted otaku college student, encounters an angelic elementary schooler!?\nThe moment she sees her sister's new friend, Hana-chan, Miyako's heart won't stop pounding!!\nShe struggles to somehow become friends with Hana-chan, but...\nA \"I want to be friends with this super cute girl\" sketch comedy begins♪"
}