{
  "studio": "Production I.G",
  "source": "Manga",
  "episodes": 12,
  "trailerYoutubeId": "rP--uJZu3eo",
  "averageScore": 68,
  "relatedAnimeIds": [],
  "zh": "以中世紀的法蘭西王國為舞台，講述了在百年戰爭的時代，身為最強魔女同時也是聖女的瑪利亞十分厭惡戰爭，她擁有的強大魔力足以讓紛爭消失。然而，如果她失去了自己的處女之身，那麼屆時也將失去強大的力量。",
  "ja": "中世フランス王国を舞台に、百年戦争の時代において、最強の魔女でありながら聖女でもあるマリアは戦争を非常に嫌っており、彼女の強大な魔力は争いを鎮めるほどであった。しかし、もし彼女が処女を喪失すれば、その強大な力も失われてしまうのだった。",
  "en": "In medieval France during the Hundred Years' War, Maria, a powerful and compassionate witch, despises the ongoing conflict. With her immense magical power, she attempts to stop the war and bring peace. However, her actions attract the attention of the heavens. The Archangel Michael decrees that Maria will lose her magic if she loses her virginity, setting the stage for a story about faith, war, and the complexities of human nature."
}